chromedriver_binary_sync/__init__.py
chromedriver_binary_sync-0.2.1.dist-info/LICENSE
chromedriver_binary_sync-0.2.1.dist-info/METADATA
chromedriver_binary_sync-0.2.1.dist-info/WHEEL
chromedriver_binary_sync-0.2.1.dist-info/top_level.txt
chromedriver_binary_sync-0.2.1.dist-info/RECORD
