Metadata-Version: 2.1
Name: chromedriver-binary-sync
Version: 0.2.1
Summary: Installer for chromedriver. (Auto sync version to GoogleChrome)
Home-page: https://github.com/bugph0bia/chromedriver-binary-sync
Author: bugph0bia
Author-email: 
License: MIT
Platform: UNKNOWN
Classifier: Topic :: Software Development :: Testing
Classifier: Topic :: System :: Installation/Setup
Classifier: Topic :: Software Development :: Libraries :: Python Modules
Classifier: License :: OSI Approved :: MIT License
Classifier: Operating System :: OS Independent
License-File: LICENSE
Requires-Dist: chromedriver-binary-auto >=0.3.1
